py4pnn/__init__.py
py4pnn/distance.py
py4pnn/p_nearest_neighbors.py
py4pnn-0.0.3.dist-info/METADATA
py4pnn-0.0.3.dist-info/WHEEL
py4pnn-0.0.3.dist-info/top_level.txt
py4pnn-0.0.3.dist-info/RECORD
