Metadata-Version: 2.1
Name: py4pnn
Version: 0.0.3
Summary: Pseudo Nearest Neighbors Python Library
Home-page: https://github.com/luthfi118/py4pnn
Author: Mgs. M. Luthfi Ramadhan
Author-email: luthfir96@gmail.com
License: UNKNOWN
Platform: UNKNOWN
Classifier: Programming Language :: Python :: 3
Classifier: License :: OSI Approved :: MIT License
Classifier: Operating System :: OS Independent
Requires-Python: >=3.7
